singleton_type/__init__.py
singleton_type/pkg_meta.py
singleton_type/py.typed
singleton_type-0.0.5.dist-info/LICENSE
singleton_type-0.0.5.dist-info/METADATA
singleton_type-0.0.5.dist-info/WHEEL
singleton_type-0.0.5.dist-info/entry_points.txt
singleton_type-0.0.5.dist-info/top_level.txt
singleton_type-0.0.5.dist-info/RECORD
